{"ref":"f11fc623-99f9-41bb-85e0-36fe536239e2","syncData":{"version":2,"machineId":"b36e5464-47ec-410f-ba67-0d239f5c3871","content":"{\"settings\":\"{\\n    \\\"workbench.colorCustomizations\\\": {\\n        \\\"statusBar.background\\\": \\\"#121016\\\",\\n        \\\"statusBar.debuggingBackground\\\": \\\"#121016\\\",\\n        \\\"statusBar.debuggingForeground\\\": \\\"#525156\\\",\\n        \\\"debugToolBar.background\\\": \\\"#121016\\\",\\n    },\\n    \\\"[dart]\\\": {\\n        \\\"editor.formatOnSave\\\": false,\\n        \\\"editor.formatOnType\\\": true,\\n        \\\"editor.selectionHighlight\\\": false,\\n        \\\"editor.suggest.snippetsPreventQuickSuggestions\\\": false,\\n        \\\"editor.suggestSelection\\\": \\\"first\\\",\\n        \\\"editor.tabCompletion\\\": \\\"onlySnippets\\\",\\n        \\\"editor.wordBasedSuggestions\\\": \\\"off\\\"\\n    },\\n}\"}"}}